CalculateAndPermutations16_qjarishekka/Calc/Task.py
CalculateAndPermutations16_qjarishekka/Calc/__init__.py
CalculateAndPermutations16_qjarishekka/Comb/Comb.py
CalculateAndPermutations16_qjarishekka/Comb/__init__.py
CalculateAndPermutations16_qjarishekka-1.2.4.dist-info/LICENSE
CalculateAndPermutations16_qjarishekka-1.2.4.dist-info/METADATA
CalculateAndPermutations16_qjarishekka-1.2.4.dist-info/WHEEL
CalculateAndPermutations16_qjarishekka-1.2.4.dist-info/top_level.txt
CalculateAndPermutations16_qjarishekka-1.2.4.dist-info/RECORD
