Metadata-Version: 2.1
Name: CalculateAndPermutations16_qjarishekka
Version: 1.2.4
Summary: calculate a ecuation given as an array and calculate combinations permutations and factorial
Author-email: Qjari Shekka <1032234412@pfur.ru>
Project-URL: Homepage, https://https://github.com/qjarishekka/CalculateAndPermutations16t
Project-URL: Issues, https://https://github.com/qjarishekka/CalculateAndPermutations16/issues
Classifier: Programming Language :: Python :: 3
Classifier: License :: OSI Approved :: MIT License
Classifier: Operating System :: OS Independent
Requires-Python: >=3.12.0
License-File: LICENSE
